main_server/__init__.py
main_server/main.py
main_server/apps/__init__.py
main_server/config/__init__.py
main_server/config/routes.py
main_server/config/settings.py
viyu/__init__.py
viyu/cli.py
viyu/commands/__init__.py
viyu/commands/add_app.py
viyu/commands/create_server.py
viyu_cli-1.0.0.dist-info/METADATA
viyu_cli-1.0.0.dist-info/WHEEL
viyu_cli-1.0.0.dist-info/entry_points.txt
viyu_cli-1.0.0.dist-info/top_level.txt
viyu_cli-1.0.0.dist-info/RECORD
