Metadata-Version: 2.2
Name: viyu-cli
Version: 1.0.0
Summary: A custom Python CLI framework for managing server projects and apps
Home-page: https://github.com/yourusername/viyu-cli
Author: Your Name
Author-email: your.email@example.com
License: MIT
Classifier: Programming Language :: Python :: 3
Classifier: License :: OSI Approved :: MIT License
Classifier: Operating System :: OS Independent
Requires-Python: >=3.6
Dynamic: author
Dynamic: author-email
Dynamic: classifier
Dynamic: description
Dynamic: description-content-type
Dynamic: home-page
Dynamic: license
Dynamic: requires-python
Dynamic: summary
